simlearn/PyStar.py
simlearn/__init__.py
simlearn/gui/LJ2D.py
simlearn/gui/LJ3D.py
simlearn/gui/__init__.py
simlearn/gui/bot.py
simlearn/gui/pV.py
simlearn/gui/star.py
simlearn/gui/worker.py
simlearn/gui/espresso_scripts/__init__.py
simlearn/gui/espresso_scripts/eLJ2D.py
simlearn/gui/espresso_scripts/eLJ3D.py
simlearn/gui/espresso_scripts/eOB.py
simlearn/gui/espresso_scripts/ebot.py
simlearn/gui/espresso_scripts/ebuckyball.py
simlearn/gui/espresso_scripts/estar.py
simlearn/gui/espresso_scripts/etools.py
simlearn/gui/plotter/LJND.py
simlearn/gui/plotter/__init__.py
simlearn/gui/plotter/bot.py
simlearn/gui/plotter/pV.py
simlearn/gui/plotter/star.py
simlearn/gui/ui/LJ2D.py
simlearn/gui/ui/LJ3D.py
simlearn/gui/ui/__init__.py
simlearn/gui/ui/pV.py
simlearn/gui/ui/resource_rc.py
simlearn/gui/ui/star.py
simlearn/gui/ui/welcome.py
simlearn-1.0.0.dist-info/LICENSE.txt
simlearn-1.0.0.dist-info/METADATA
simlearn-1.0.0.dist-info/WHEEL
simlearn-1.0.0.dist-info/top_level.txt
simlearn-1.0.0.dist-info/RECORD
