Metadata-Version: 2.1
Name: simlearn
Version: 1.0.0
Summary: Simlearn is a way how to teach/learn about simulations with a joy. PyStar is a main application of it.
Home-page: https://gitlab.com/alexander.d.kazakov/pystar
Author: Alexander D. Kazakov
Author-email: alexander.d.kazakov@gmail.com
License: GNU
Keywords: simulations,molecular dynamics,LJ,CG
Platform: UNKNOWN
Classifier: Development Status :: 4 - Beta
Classifier: Intended Audience :: Developers
Classifier: Topic :: Software Development :: Build Tools
Classifier: License :: OSI Approved :: MIT License
Classifier: Programming Language :: Python :: 3
Classifier: Programming Language :: Python :: 3.8
Classifier: Programming Language :: Python :: 3.9
Requires-Python: >=3.8
Requires-Dist: PyOpenGL
Requires-Dist: matplotlib
Requires-Dist: numpy
Requires-Dist: pyqt5
Requires-Dist: pyqt5-sip
Requires-Dist: pyqt5-tools
Requires-Dist: pyqtgraph
